panax/__init__.py
panax/database.py
panax/permission.py
panax/request.py
panax/tool.py
panax/utils.py
panax/default_views/__init__.py
panax/default_views/auto_view.py
panax/default_views/file_view.py
panax/panax_views/__init__.py
panax/panax_views/auto_view.py
panax/panax_views/file_view.py
panax/template/__init__.py
panax/template/app.py
panax/template/models.py
panax/template/config/__init__.py
panax/template/config/sql_template.py
panax/template/views/__init__.py
panax/template/views/users_view.py
panax/utils/__init__.py
panax/utils/aes.py
panax/utils/db_helper.py
panax/utils/jwt_helper.py
panax/utils/request_helper.py
panax/utils/rsa.py
panax-0.0.66.dist-info/METADATA
panax-0.0.66.dist-info/WHEEL
panax-0.0.66.dist-info/entry_points.txt
panax-0.0.66.dist-info/top_level.txt
panax-0.0.66.dist-info/RECORD
